macvpnhelper/__init__.py
macvpnhelper-0.1.0.data/scripts/macvpnhelper
macvpnhelper-0.1.0.dist-info/METADATA
macvpnhelper-0.1.0.dist-info/RECORD
macvpnhelper-0.1.0.dist-info/WHEEL
macvpnhelper-0.1.0.dist-info/top_level.txt
