Metadata-Version: 2.1
Name: macvpnhelper
Version: 0.1.0
Summary: Tool to monitor and restart Mac VPN.
Home-page: https://github.com/llurkingllama/macvpnhelper/
Author: Ryan Shea
Author-email: rshea@aviatainc.com
License: MIT License
Requires-Dist: keyring
